setup.cfg
setup.py
decred/__init__.py
decred/core/__init__.py
decred/core/block.py
decred/core/chaincfg.py
decred/core/key.py
decred/core/serialize.py
decred/core/transaction.py
decred/core/script/__init__.py
decred/core/script/constants.py
decred/core/script/engine.py
decred/core/script/errors.py
decred/core/script/opcode.py
decred/core/script/script.py
decred/core/script/scriptbuilder.py
decred/core/script/scriptnum.py
decred/core/script/stack.py
decred/core/script/standard.py
decred/tests/__init__.py
decred/tests/test_block.py
decred/tests/test_engine.py
decred/tests/test_scriptbuilder.py
decred/tests/test_scriptnum.py
decred/tests/test_stack.py
decred/tests/test_transaction.py
pydecred.egg-info/PKG-INFO
pydecred.egg-info/SOURCES.txt
pydecred.egg-info/dependency_links.txt
pydecred.egg-info/requires.txt
pydecred.egg-info/top_level.txt