Metadata-Version: 1.0
Name: pydecred
Version: 0.1a
Summary: Decred python library.
Home-page: https://github.com/kefkius/pydecred
Author: Tyler Willis
Author-email: kefkiusrex@gmail.com
License: UNKNOWN
Keywords: decred
Platform: UNKNOWN
